aioservicekit/__init__.py
aioservicekit/channels.py
aioservicekit/events.py
aioservicekit/groups.py
aioservicekit/services.py
aioservicekit/tasks.py
aioservicekit/utils.py
aioservicekit-0.6.0.dist-info/licenses/LICENSE
aioservicekit-0.6.0.dist-info/METADATA
aioservicekit-0.6.0.dist-info/WHEEL
aioservicekit-0.6.0.dist-info/top_level.txt
aioservicekit-0.6.0.dist-info/RECORD
