Metadata-Version: 2.4
Name: aioservicekit
Version: 0.6.0
Summary: A framework for creating asynchronous services. It helps to create nanoservices (like microservices, but for microservices), control their life cycle and organize communications.
Home-page: https://github.com/8ByteCore8/aioservicekit
Author: Bohdan Kushnir
Author-email: 
License:                                  Apache License
Project-URL: Source, https://github.com/8ByteCore8/aioservicekit
Keywords: async,asyncio,service,microservice,nanoservice
Classifier: Development Status :: 3 - Alpha
Classifier: Intended Audience :: Developers
Classifier: License :: OSI Approved :: Apache Software License
Classifier: Programming Language :: Python :: 3.9
Classifier: Programming Language :: Python :: 3.10
Classifier: Programming Language :: Python :: 3.11
Classifier: Programming Language :: Python :: 3.12
Classifier: Programming Language :: Python :: 3.13
Requires: exceptiongroup
Requires-Python: >=3.9
License-File: LICENSE
Provides-Extra: test
Requires-Dist: ruff>=0.7.4; extra == "test"
Dynamic: author
Dynamic: classifier
Dynamic: description
Dynamic: description-content-type
Dynamic: home-page
Dynamic: keywords
Dynamic: license
Dynamic: license-file
Dynamic: project-url
Dynamic: provides-extra
Dynamic: requires
Dynamic: requires-python
Dynamic: summary
